abc_matlab.py-0.1.data/scripts/abc_matlab.py
abc_matlab.py-0.1.data/scripts/anonymous_matlab.py
dokr_pkg/__init__.py
dokr_pkg/anonymous_matlab.py
abc_matlab.py-0.1.dist-info/METADATA
abc_matlab.py-0.1.dist-info/WHEEL
abc_matlab.py-0.1.dist-info/top_level.txt
abc_matlab.py-0.1.dist-info/RECORD
